dataverse_ops/__init__.py
dataverse_ops/dataverse_ops.py
pyDataverseOps-0.1.2.dist-info/METADATA
pyDataverseOps-0.1.2.dist-info/WHEEL
pyDataverseOps-0.1.2.dist-info/top_level.txt
pyDataverseOps-0.1.2.dist-info/RECORD
