Metadata-Version: 2.1
Name: pyDataverseOps
Version: 0.1.2
Summary: A Python library to facilitate operations on Microsoft Dataverse
Home-page: https://github.com/ray2199/pyDataverseOps.git
Author: Akash Yadav
Author-email: akash21091999@gmail.com
License: UNKNOWN
Platform: UNKNOWN
Classifier: Development Status :: 3 - Alpha
Classifier: Intended Audience :: Developers
Classifier: Topic :: Software Development :: Libraries :: Python Modules
Classifier: License :: OSI Approved :: MIT License
Classifier: Programming Language :: Python :: 3
Classifier: Programming Language :: Python :: 3.6
Classifier: Programming Language :: Python :: 3.7
Classifier: Programming Language :: Python :: 3.8
Classifier: Programming Language :: Python :: 3.9
Classifier: Programming Language :: Python :: 3.10
Classifier: Operating System :: OS Independent
Requires-Python: >=3.6
Requires-Dist: pandas >=1.0
Requires-Dist: requests >=2.20
